{
  "squares": {
      "__root":       "__this is a system key__",
      "text1"       : "このページは、最新のreact（16.12.0）レンダリング機能をテストするために作成されています",
      "text2" : "以下のブロックのカウントを増やしてみて、それらと対話してみてください。",
      "text3":"FPSフレームが約4500個のアイテム数でドロップするのがわかります。",
      "text4":"任意の数に設定して、世界が燃えるのを見ることができます🔥",
      "fps": "フレーム毎秒",
      "text5":"ここでブロック数を設定します",
      "text5_1":"ここでブロックサイズを設定します",
      "text4_1":"プレーンレンダーfpsとレンダーインタラクティブfpsの違いも確認できます。",
      "text4_2":"特にChromeで顕著です。ブロック数を〜1500に設定してから、それらと対話してfpsの違いを確認してください。"
  }
}